{
  "version": "8",
  "dialect": "postgres",
  "id": "18c67514-6dde-4ad5-8db5-5695571f5dc7",
  "prevIds": [
    "1660d5e9-ebb4-47dd-b4be-f917d829c1f9"
  ],
  "ddl": [
    {
      "values": [
        "CHROME",
        "FIREFOX",
        "SAFARI",
        "EDGE",
        "OPERA"
      ],
      "name": "category",
      "entityType": "enums",
      "schema": "public"
    },
    {
      "values": [
        "PUSH",
        "EMAIL",
        "SMS",
        "IN_APP"
      ],
      "name": "channelType",
      "entityType": "enums",
      "schema": "public"
    },
    {
      "values": [
        "PENDING",
        "SENT",
        "DELIVERED",
        "FAILED",
        "CLICKED"
      ],
      "name": "delivery_status",
      "entityType": "enums",
      "schema": "public"
    },
    {
      "values": [
        "ACTIVE",
        "INACTIVE",
        "EXPIRED"
      ],
      "name": "device_status",
      "entityType": "enums",
      "schema": "public"
    },
    {
      "values": [
        "NOTIFICATION_SENT",
        "NOTIFICATION_DELIVERED",
        "NOTIFICATION_FAILED",
        "NOTIFICATION_CLICKED",
        "WORKFLOW_COMPLETED",
        "WORKFLOW_FAILED"
      ],
      "name": "hookEvent",
      "entityType": "enums",
      "schema": "public"
    },
    {
      "values": [
        "PENDING",
        "SENT",
        "DELIVERED",
        "FAILED",
        "SCHEDULED"
      ],
      "name": "notification_status",
      "entityType": "enums",
      "schema": "public"
    },
    {
      "values": [
        "IOS",
        "ANDROID",
        "WEB"
      ],
      "name": "platform",
      "entityType": "enums",
      "schema": "public"
    },
    {
      "values": [
        "RUNNING",
        "COMPLETED",
        "FAILED",
        "CANCELLED"
      ],
      "name": "workflowExecutionStatus",
      "entityType": "enums",
      "schema": "public"
    },
    {
      "values": [
        "DRAFT",
        "ACTIVE",
        "PAUSED",
        "ARCHIVED"
      ],
      "name": "workflowStatus",
      "entityType": "enums",
      "schema": "public"
    },
    {
      "values": [
        "SEND",
        "DELAY",
        "FILTER",
        "DIGEST",
        "BRANCH"
      ],
      "name": "workflowStepType",
      "entityType": "enums",
      "schema": "public"
    },
    {
      "values": [
        "EVENT",
        "SCHEDULED",
        "MANUAL"
      ],
      "name": "workflowTriggerType",
      "entityType": "enums",
      "schema": "public"
    },
    {
      "isRlsEnabled": false,
      "name": "apiKey",
      "entityType": "tables",
      "schema": "public"
    },
    {
      "isRlsEnabled": false,
      "name": "app",
      "entityType": "tables",
      "schema": "public"
    },
    {
      "isRlsEnabled": false,
      "name": "channel",
      "entityType": "tables",
      "schema": "public"
    },
    {
      "isRlsEnabled": false,
      "name": "deliveryLog",
      "entityType": "tables",
      "schema": "public"
    },
    {
      "isRlsEnabled": false,
      "name": "device",
      "entityType": "tables",
      "schema": "public"
    },
    {
      "isRlsEnabled": false,
      "name": "hook",
      "entityType": "tables",
      "schema": "public"
    },
    {
      "isRlsEnabled": false,
      "name": "notification",
      "entityType": "tables",
      "schema": "public"
    },
    {
      "isRlsEnabled": false,
      "name": "subscriber",
      "entityType": "tables",
      "schema": "public"
    },
    {
      "isRlsEnabled": false,
      "name": "subscriberDevice",
      "entityType": "tables",
      "schema": "public"
    },
    {
      "isRlsEnabled": false,
      "name": "subscriberPreference",
      "entityType": "tables",
      "schema": "public"
    },
    {
      "isRlsEnabled": false,
      "name": "template",
      "entityType": "tables",
      "schema": "public"
    },
    {
      "isRlsEnabled": false,
      "name": "workflow",
      "entityType": "tables",
      "schema": "public"
    },
    {
      "isRlsEnabled": false,
      "name": "workflowExecution",
      "entityType": "tables",
      "schema": "public"
    },
    {
      "isRlsEnabled": false,
      "name": "workflowStep",
      "entityType": "tables",
      "schema": "public"
    },
    {
      "type": "uuid",
      "typeSchema": null,
      "notNull": true,
      "dimensions": 0,
      "default": null,
      "generated": null,
      "identity": null,
      "name": "id",
      "entityType": "columns",
      "schema": "public",
      "table": "apiKey"
    },
    {
      "type": "uuid",
      "typeSchema": null,
      "notNull": true,
      "dimensions": 0,
      "default": null,
      "generated": null,
      "identity": null,
      "name": "appId",
      "entityType": "columns",
      "schema": "public",
      "table": "apiKey"
    },
    {
      "type": "text",
      "typeSchema": null,
      "notNull": true,
      "dimensions": 0,
      "default": null,
      "generated": null,
      "identity": null,
      "name": "name",
      "entityType": "columns",
      "schema": "public",
      "table": "apiKey"
    },
    {
      "type": "text",
      "typeSchema": null,
      "notNull": true,
      "dimensions": 0,
      "default": null,
      "generated": null,
      "identity": null,
      "name": "key",
      "entityType": "columns",
      "schema": "public",
      "table": "apiKey"
    },
    {
      "type": "jsonb",
      "typeSchema": null,
      "notNull": false,
      "dimensions": 0,
      "default": null,
      "generated": null,
      "identity": null,
      "name": "permissions",
      "entityType": "columns",
      "schema": "public",
      "table": "apiKey"
    },
    {
      "type": "boolean",
      "typeSchema": null,
      "notNull": false,
      "dimensions": 0,
      "default": "true",
      "generated": null,
      "identity": null,
      "name": "isActive",
      "entityType": "columns",
      "schema": "public",
      "table": "apiKey"
    },
    {
      "type": "timestamp(3) with time zone",
      "typeSchema": null,
      "notNull": false,
      "dimensions": 0,
      "default": null,
      "generated": null,
      "identity": null,
      "name": "lastUsedAt",
      "entityType": "columns",
      "schema": "public",
      "table": "apiKey"
    },
    {
      "type": "timestamp(3) with time zone",
      "typeSchema": null,
      "notNull": false,
      "dimensions": 0,
      "default": null,
      "generated": null,
      "identity": null,
      "name": "expiresAt",
      "entityType": "columns",
      "schema": "public",
      "table": "apiKey"
    },
    {
      "type": "timestamp(3) with time zone",
      "typeSchema": null,
      "notNull": true,
      "dimensions": 0,
      "default": "now()",
      "generated": null,
      "identity": null,
      "name": "createdAt",
      "entityType": "columns",
      "schema": "public",
      "table": "apiKey"
    },
    {
      "type": "timestamp(3) with time zone",
      "typeSchema": null,
      "notNull": true,
      "dimensions": 0,
      "default": "now()",
      "generated": null,
      "identity": null,
      "name": "updatedAt",
      "entityType": "columns",
      "schema": "public",
      "table": "apiKey"
    },
    {
      "type": "uuid",
      "typeSchema": null,
      "notNull": true,
      "dimensions": 0,
      "default": null,
      "generated": null,
      "identity": null,
      "name": "id",
      "entityType": "columns",
      "schema": "public",
      "table": "app"
    },
    {
      "type": "text",
      "typeSchema": null,
      "notNull": true,
      "dimensions": 0,
      "default": null,
      "generated": null,
      "identity": null,
      "name": "name",
      "entityType": "columns",
      "schema": "public",
      "table": "app"
    },
    {
      "type": "text",
      "typeSchema": null,
      "notNull": true,
      "dimensions": 0,
      "default": null,
      "generated": null,
      "identity": null,
      "name": "slug",
      "entityType": "columns",
      "schema": "public",
      "table": "app"
    },
    {
      "type": "text",
      "typeSchema": null,
      "notNull": false,
      "dimensions": 0,
      "default": null,
      "generated": null,
      "identity": null,
      "name": "description",
      "entityType": "columns",
      "schema": "public",
      "table": "app"
    },
    {
      "type": "text",
      "typeSchema": null,
      "notNull": true,
      "dimensions": 0,
      "default": null,
      "generated": null,
      "identity": null,
      "name": "apiKey",
      "entityType": "columns",
      "schema": "public",
      "table": "app"
    },
    {
      "type": "text",
      "typeSchema": null,
      "notNull": false,
      "dimensions": 0,
      "default": null,
      "generated": null,
      "identity": null,
      "name": "fcmServerKey",
      "entityType": "columns",
      "schema": "public",
      "table": "app"
    },
    {
      "type": "text",
      "typeSchema": null,
      "notNull": false,
      "dimensions": 0,
      "default": null,
      "generated": null,
      "identity": null,
      "name": "fcmProjectId",
      "entityType": "columns",
      "schema": "public",
      "table": "app"
    },
    {
      "type": "text",
      "typeSchema": null,
      "notNull": false,
      "dimensions": 0,
      "default": null,
      "generated": null,
      "identity": null,
      "name": "apnsCertificate",
      "entityType": "columns",
      "schema": "public",
      "table": "app"
    },
    {
      "type": "text",
      "typeSchema": null,
      "notNull": false,
      "dimensions": 0,
      "default": null,
      "generated": null,
      "identity": null,
      "name": "apnsKeyId",
      "entityType": "columns",
      "schema": "public",
      "table": "app"
    },
    {
      "type": "text",
      "typeSchema": null,
      "notNull": false,
      "dimensions": 0,
      "default": null,
      "generated": null,
      "identity": null,
      "name": "apnsTeamId",
      "entityType": "columns",
      "schema": "public",
      "table": "app"
    },
    {
      "type": "text",
      "typeSchema": null,
      "notNull": false,
      "dimensions": 0,
      "default": null,
      "generated": null,
      "identity": null,
      "name": "bundleId",
      "entityType": "columns",
      "schema": "public",
      "table": "app"
    },
    {
      "type": "text",
      "typeSchema": null,
      "notNull": false,
      "dimensions": 0,
      "default": null,
      "generated": null,
      "identity": null,
      "name": "vapidPublicKey",
      "entityType": "columns",
      "schema": "public",
      "table": "app"
    },
    {
      "type": "text",
      "typeSchema": null,
      "notNull": false,
      "dimensions": 0,
      "default": null,
      "generated": null,
      "identity": null,
      "name": "vapidPrivateKey",
      "entityType": "columns",
      "schema": "public",
      "table": "app"
    },
    {
      "type": "text",
      "typeSchema": null,
      "notNull": false,
      "dimensions": 0,
      "default": null,
      "generated": null,
      "identity": null,
      "name": "vapidSubject",
      "entityType": "columns",
      "schema": "public",
      "table": "app"
    },
    {
      "type": "boolean",
      "typeSchema": null,
      "notNull": true,
      "dimensions": 0,
      "default": "true",
      "generated": null,
      "identity": null,
      "name": "isActive",
      "entityType": "columns",
      "schema": "public",
      "table": "app"
    },
    {
      "type": "timestamp(3) with time zone",
      "typeSchema": null,
      "notNull": true,
      "dimensions": 0,
      "default": "now()",
      "generated": null,
      "identity": null,
      "name": "createdAt",
      "entityType": "columns",
      "schema": "public",
      "table": "app"
    },
    {
      "type": "timestamp(3) with time zone",
      "typeSchema": null,
      "notNull": true,
      "dimensions": 0,
      "default": "now()",
      "generated": null,
      "identity": null,
      "name": "updatedAt",
      "entityType": "columns",
      "schema": "public",
      "table": "app"
    },
    {
      "type": "uuid",
      "typeSchema": null,
      "notNull": true,
      "dimensions": 0,
      "default": null,
      "generated": null,
      "identity": null,
      "name": "id",
      "entityType": "columns",
      "schema": "public",
      "table": "channel"
    },
    {
      "type": "uuid",
      "typeSchema": null,
      "notNull": true,
      "dimensions": 0,
      "default": null,
      "generated": null,
      "identity": null,
      "name": "appId",
      "entityType": "columns",
      "schema": "public",
      "table": "channel"
    },
    {
      "type": "text",
      "typeSchema": null,
      "notNull": true,
      "dimensions": 0,
      "default": null,
      "generated": null,
      "identity": null,
      "name": "name",
      "entityType": "columns",
      "schema": "public",
      "table": "channel"
    },
    {
      "type": "channelType",
      "typeSchema": "public",
      "notNull": true,
      "dimensions": 0,
      "default": null,
      "generated": null,
      "identity": null,
      "name": "type",
      "entityType": "columns",
      "schema": "public",
      "table": "channel"
    },
    {
      "type": "jsonb",
      "typeSchema": null,
      "notNull": false,
      "dimensions": 0,
      "default": null,
      "generated": null,
      "identity": null,
      "name": "config",
      "entityType": "columns",
      "schema": "public",
      "table": "channel"
    },
    {
      "type": "boolean",
      "typeSchema": null,
      "notNull": true,
      "dimensions": 0,
      "default": "true",
      "generated": null,
      "identity": null,
      "name": "isActive",
      "entityType": "columns",
      "schema": "public",
      "table": "channel"
    },
    {
      "type": "timestamp(3) with time zone",
      "typeSchema": null,
      "notNull": true,
      "dimensions": 0,
      "default": "now()",
      "generated": null,
      "identity": null,
      "name": "createdAt",
      "entityType": "columns",
      "schema": "public",
      "table": "channel"
    },
    {
      "type": "timestamp(3) with time zone",
      "typeSchema": null,
      "notNull": true,
      "dimensions": 0,
      "default": "now()",
      "generated": null,
      "identity": null,
      "name": "updatedAt",
      "entityType": "columns",
      "schema": "public",
      "table": "channel"
    },
    {
      "type": "uuid",
      "typeSchema": null,
      "notNull": true,
      "dimensions": 0,
      "default": null,
      "generated": null,
      "identity": null,
      "name": "id",
      "entityType": "columns",
      "schema": "public",
      "table": "deliveryLog"
    },
    {
      "type": "uuid",
      "typeSchema": null,
      "notNull": true,
      "dimensions": 0,
      "default": null,
      "generated": null,
      "identity": null,
      "name": "notificationId",
      "entityType": "columns",
      "schema": "public",
      "table": "deliveryLog"
    },
    {
      "type": "uuid",
      "typeSchema": null,
      "notNull": true,
      "dimensions": 0,
      "default": null,
      "generated": null,
      "identity": null,
      "name": "deviceId",
      "entityType": "columns",
      "schema": "public",
      "table": "deliveryLog"
    },
    {
      "type": "delivery_status",
      "typeSchema": "public",
      "notNull": true,
      "dimensions": 0,
      "default": null,
      "generated": null,
      "identity": null,
      "name": "status",
      "entityType": "columns",
      "schema": "public",
      "table": "deliveryLog"
    },
    {
      "type": "jsonb",
      "typeSchema": null,
      "notNull": false,
      "dimensions": 0,
      "default": null,
      "generated": null,
      "identity": null,
      "name": "providerResponse",
      "entityType": "columns",
      "schema": "public",
      "table": "deliveryLog"
    },
    {
      "type": "text",
      "typeSchema": null,
      "notNull": false,
      "dimensions": 0,
      "default": null,
      "generated": null,
      "identity": null,
      "name": "errorMessage",
      "entityType": "columns",
      "schema": "public",
      "table": "deliveryLog"
    },
    {
      "type": "integer",
      "typeSchema": null,
      "notNull": false,
      "dimensions": 0,
      "default": "1",
      "generated": null,
      "identity": null,
      "name": "attemptCount",
      "entityType": "columns",
      "schema": "public",
      "table": "deliveryLog"
    },
    {
      "type": "timestamp(3) with time zone",
      "typeSchema": null,
      "notNull": false,
      "dimensions": 0,
      "default": null,
      "generated": null,
      "identity": null,
      "name": "sentAt",
      "entityType": "columns",
      "schema": "public",
      "table": "deliveryLog"
    },
    {
      "type": "timestamp(3) with time zone",
      "typeSchema": null,
      "notNull": false,
      "dimensions": 0,
      "default": null,
      "generated": null,
      "identity": null,
      "name": "deliveredAt",
      "entityType": "columns",
      "schema": "public",
      "table": "deliveryLog"
    },
    {
      "type": "timestamp(3) with time zone",
      "typeSchema": null,
      "notNull": false,
      "dimensions": 0,
      "default": null,
      "generated": null,
      "identity": null,
      "name": "openedAt",
      "entityType": "columns",
      "schema": "public",
      "table": "deliveryLog"
    },
    {
      "type": "timestamp(3) with time zone",
      "typeSchema": null,
      "notNull": false,
      "dimensions": 0,
      "default": null,
      "generated": null,
      "identity": null,
      "name": "clickedAt",
      "entityType": "columns",
      "schema": "public",
      "table": "deliveryLog"
    },
    {
      "type": "text",
      "typeSchema": null,
      "notNull": false,
      "dimensions": 0,
      "default": null,
      "generated": null,
      "identity": null,
      "name": "platform",
      "entityType": "columns",
      "schema": "public",
      "table": "deliveryLog"
    },
    {
      "type": "text",
      "typeSchema": null,
      "notNull": false,
      "dimensions": 0,
      "default": null,
      "generated": null,
      "identity": null,
      "name": "userAgent",
      "entityType": "columns",
      "schema": "public",
      "table": "deliveryLog"
    },
    {
      "type": "text",
      "typeSchema": null,
      "notNull": false,
      "dimensions": 0,
      "default": null,
      "generated": null,
      "identity": null,
      "name": "appVersion",
      "entityType": "columns",
      "schema": "public",
      "table": "deliveryLog"
    },
    {
      "type": "text",
      "typeSchema": null,
      "notNull": false,
      "dimensions": 0,
      "default": null,
      "generated": null,
      "identity": null,
      "name": "osVersion",
      "entityType": "columns",
      "schema": "public",
      "table": "deliveryLog"
    },
    {
      "type": "timestamp(3) with time zone",
      "typeSchema": null,
      "notNull": true,
      "dimensions": 0,
      "default": "now()",
      "generated": null,
      "identity": null,
      "name": "createdAt",
      "entityType": "columns",
      "schema": "public",
      "table": "deliveryLog"
    },
    {
      "type": "timestamp(3) with time zone",
      "typeSchema": null,
      "notNull": true,
      "dimensions": 0,
      "default": "now()",
      "generated": null,
      "identity": null,
      "name": "updatedAt",
      "entityType": "columns",
      "schema": "public",
      "table": "deliveryLog"
    },
    {
      "type": "uuid",
      "typeSchema": null,
      "notNull": true,
      "dimensions": 0,
      "default": null,
      "generated": null,
      "identity": null,
      "name": "id",
      "entityType": "columns",
      "schema": "public",
      "table": "device"
    },
    {
      "type": "uuid",
      "typeSchema": null,
      "notNull": true,
      "dimensions": 0,
      "default": null,
      "generated": null,
      "identity": null,
      "name": "appId",
      "entityType": "columns",
      "schema": "public",
      "table": "device"
    },
    {
      "type": "uuid",
      "typeSchema": null,
      "notNull": false,
      "dimensions": 0,
      "default": null,
      "generated": null,
      "identity": null,
      "name": "subscriberId",
      "entityType": "columns",
      "schema": "public",
      "table": "device"
    },
    {
      "type": "text",
      "typeSchema": null,
      "notNull": true,
      "dimensions": 0,
      "default": null,
      "generated": null,
      "identity": null,
      "name": "token",
      "entityType": "columns",
      "schema": "public",
      "table": "device"
    },
    {
      "type": "category",
      "typeSchema": "public",
      "notNull": false,
      "dimensions": 0,
      "default": null,
      "generated": null,
      "identity": null,
      "name": "category",
      "entityType": "columns",
      "schema": "public",
      "table": "device"
    },
    {
      "type": "platform",
      "typeSchema": "public",
      "notNull": true,
      "dimensions": 0,
      "default": null,
      "generated": null,
      "identity": null,
      "name": "platform",
      "entityType": "columns",
      "schema": "public",
      "table": "device"
    },
    {
      "type": "text",
      "typeSchema": null,
      "notNull": false,
      "dimensions": 0,
      "default": null,
      "generated": null,
      "identity": null,
      "name": "userId",
      "entityType": "columns",
      "schema": "public",
      "table": "device"
    },
    {
      "type": "device_status",
      "typeSchema": "public",
      "notNull": true,
      "dimensions": 0,
      "default": "'ACTIVE'",
      "generated": null,
      "identity": null,
      "name": "status",
      "entityType": "columns",
      "schema": "public",
      "table": "device"
    },
    {
      "type": "jsonb",
      "typeSchema": null,
      "notNull": false,
      "dimensions": 0,
      "default": null,
      "generated": null,
      "identity": null,
      "name": "metadata",
      "entityType": "columns",
      "schema": "public",
      "table": "device"
    },
    {
      "type": "text",
      "typeSchema": null,
      "notNull": false,
      "dimensions": 0,
      "default": null,
      "generated": null,
      "identity": null,
      "name": "webPushP256dh",
      "entityType": "columns",
      "schema": "public",
      "table": "device"
    },
    {
      "type": "text",
      "typeSchema": null,
      "notNull": false,
      "dimensions": 0,
      "default": null,
      "generated": null,
      "identity": null,
      "name": "webPushAuth",
      "entityType": "columns",
      "schema": "public",
      "table": "device"
    },
    {
      "type": "timestamp(3) with time zone",
      "typeSchema": null,
      "notNull": false,
      "dimensions": 0,
      "default": null,
      "generated": null,
      "identity": null,
      "name": "lastSeenAt",
      "entityType": "columns",
      "schema": "public",
      "table": "device"
    },
    {
      "type": "timestamp(3) with time zone",
      "typeSchema": null,
      "notNull": true,
      "dimensions": 0,
      "default": "now()",
      "generated": null,
      "identity": null,
      "name": "createdAt",
      "entityType": "columns",
      "schema": "public",
      "table": "device"
    },
    {
      "type": "timestamp(3) with time zone",
      "typeSchema": null,
      "notNull": true,
      "dimensions": 0,
      "default": "now()",
      "generated": null,
      "identity": null,
      "name": "updatedAt",
      "entityType": "columns",
      "schema": "public",
      "table": "device"
    },
    {
      "type": "uuid",
      "typeSchema": null,
      "notNull": true,
      "dimensions": 0,
      "default": null,
      "generated": null,
      "identity": null,
      "name": "id",
      "entityType": "columns",
      "schema": "public",
      "table": "hook"
    },
    {
      "type": "uuid",
      "typeSchema": null,
      "notNull": true,
      "dimensions": 0,
      "default": null,
      "generated": null,
      "identity": null,
      "name": "appId",
      "entityType": "columns",
      "schema": "public",
      "table": "hook"
    },
    {
      "type": "text",
      "typeSchema": null,
      "notNull": true,
      "dimensions": 0,
      "default": null,
      "generated": null,
      "identity": null,
      "name": "name",
      "entityType": "columns",
      "schema": "public",
      "table": "hook"
    },
    {
      "type": "text",
      "typeSchema": null,
      "notNull": true,
      "dimensions": 0,
      "default": null,
      "generated": null,
      "identity": null,
      "name": "url",
      "entityType": "columns",
      "schema": "public",
      "table": "hook"
    },
    {
      "type": "text",
      "typeSchema": null,
      "notNull": false,
      "dimensions": 0,
      "default": null,
      "generated": null,
      "identity": null,
      "name": "secret",
      "entityType": "columns",
      "schema": "public",
      "table": "hook"
    },
    {
      "type": "jsonb",
      "typeSchema": null,
      "notNull": false,
      "dimensions": 0,
      "default": null,
      "generated": null,
      "identity": null,
      "name": "events",
      "entityType": "columns",
      "schema": "public",
      "table": "hook"
    },
    {
      "type": "boolean",
      "typeSchema": null,
      "notNull": true,
      "dimensions": 0,
      "default": "true",
      "generated": null,
      "identity": null,
      "name": "isActive",
      "entityType": "columns",
      "schema": "public",
      "table": "hook"
    },
    {
      "type": "timestamp(3) with time zone",
      "typeSchema": null,
      "notNull": true,
      "dimensions": 0,
      "default": "now()",
      "generated": null,
      "identity": null,
      "name": "createdAt",
      "entityType": "columns",
      "schema": "public",
      "table": "hook"
    },
    {
      "type": "timestamp(3) with time zone",
      "typeSchema": null,
      "notNull": true,
      "dimensions": 0,
      "default": "now()",
      "generated": null,
      "identity": null,
      "name": "updatedAt",
      "entityType": "columns",
      "schema": "public",
      "table": "hook"
    },
    {
      "type": "uuid",
      "typeSchema": null,
      "notNull": true,
      "dimensions": 0,
      "default": null,
      "generated": null,
      "identity": null,
      "name": "id",
      "entityType": "columns",
      "schema": "public",
      "table": "notification"
    },
    {
      "type": "uuid",
      "typeSchema": null,
      "notNull": true,
      "dimensions": 0,
      "default": null,
      "generated": null,
      "identity": null,
      "name": "appId",
      "entityType": "columns",
      "schema": "public",
      "table": "notification"
    },
    {
      "type": "text",
      "typeSchema": null,
      "notNull": true,
      "dimensions": 0,
      "default": null,
      "generated": null,
      "identity": null,
      "name": "title",
      "entityType": "columns",
      "schema": "public",
      "table": "notification"
    },
    {
      "type": "text",
      "typeSchema": null,
      "notNull": true,
      "dimensions": 0,
      "default": null,
      "generated": null,
      "identity": null,
      "name": "body",
      "entityType": "columns",
      "schema": "public",
      "table": "notification"
    },
    {
      "type": "jsonb",
      "typeSchema": null,
      "notNull": false,
      "dimensions": 0,
      "default": null,
      "generated": null,
      "identity": null,
      "name": "data",
      "entityType": "columns",
      "schema": "public",
      "table": "notification"
    },
    {
      "type": "integer",
      "typeSchema": null,
      "notNull": false,
      "dimensions": 0,
      "default": null,
      "generated": null,
      "identity": null,
      "name": "badge",
      "entityType": "columns",
      "schema": "public",
      "table": "notification"
    },
    {
      "type": "text",
      "typeSchema": null,
      "notNull": false,
      "dimensions": 0,
      "default": null,
      "generated": null,
      "identity": null,
      "name": "sound",
      "entityType": "columns",
      "schema": "public",
      "table": "notification"
    },
    {
      "type": "text",
      "typeSchema": null,
      "notNull": false,
      "dimensions": 0,
      "default": null,
      "generated": null,
      "identity": null,
      "name": "clickAction",
      "entityType": "columns",
      "schema": "public",
      "table": "notification"
    },
    {
      "type": "text",
      "typeSchema": null,
      "notNull": false,
      "dimensions": 0,
      "default": null,
      "generated": null,
      "identity": null,
      "name": "icon",
      "entityType": "columns",
      "schema": "public",
      "table": "notification"
    },
    {
      "type": "text",
      "typeSchema": null,
      "notNull": false,
      "dimensions": 0,
      "default": null,
      "generated": null,
      "identity": null,
      "name": "image",
      "entityType": "columns",
      "schema": "public",
      "table": "notification"
    },
    {
      "type": "text",
      "typeSchema": null,
      "notNull": false,
      "dimensions": 0,
      "default": null,
      "generated": null,
      "identity": null,
      "name": "imageUrl",
      "entityType": "columns",
      "schema": "public",
      "table": "notification"
    },
    {
      "type": "jsonb",
      "typeSchema": null,
      "notNull": false,
      "dimensions": 0,
      "default": null,
      "generated": null,
      "identity": null,
      "name": "targetDevices",
      "entityType": "columns",
      "schema": "public",
      "table": "notification"
    },
    {
      "type": "jsonb",
      "typeSchema": null,
      "notNull": false,
      "dimensions": 0,
      "default": null,
      "generated": null,
      "identity": null,
      "name": "platforms",
      "entityType": "columns",
      "schema": "public",
      "table": "notification"
    },
    {
      "type": "timestamp(3) with time zone",
      "typeSchema": null,
      "notNull": false,
      "dimensions": 0,
      "default": null,
      "generated": null,
      "identity": null,
      "name": "scheduledAt",
      "entityType": "columns",
      "schema": "public",
      "table": "notification"
    },
    {
      "type": "timestamp(3) with time zone",
      "typeSchema": null,
      "notNull": false,
      "dimensions": 0,
      "default": null,
      "generated": null,
      "identity": null,
      "name": "expiresAt",
      "entityType": "columns",
      "schema": "public",
      "table": "notification"
    },
    {
      "type": "notification_status",
      "typeSchema": "public",
      "notNull": true,
      "dimensions": 0,
      "default": "'PENDING'",
      "generated": null,
      "identity": null,
      "name": "status",
      "entityType": "columns",
      "schema": "public",
      "table": "notification"
    },
    {
      "type": "integer",
      "typeSchema": null,
      "notNull": true,
      "dimensions": 0,
      "default": "0",
      "generated": null,
      "identity": null,
      "name": "totalTargets",
      "entityType": "columns",
      "schema": "public",
      "table": "notification"
    },
    {
      "type": "integer",
      "typeSchema": null,
      "notNull": true,
      "dimensions": 0,
      "default": "0",
      "generated": null,
      "identity": null,
      "name": "totalSent",
      "entityType": "columns",
      "schema": "public",
      "table": "notification"
    },
    {
      "type": "integer",
      "typeSchema": null,
      "notNull": true,
      "dimensions": 0,
      "default": "0",
      "generated": null,
      "identity": null,
      "name": "totalDelivered",
      "entityType": "columns",
      "schema": "public",
      "table": "notification"
    },
    {
      "type": "integer",
      "typeSchema": null,
      "notNull": true,
      "dimensions": 0,
      "default": "0",
      "generated": null,
      "identity": null,
      "name": "totalFailed",
      "entityType": "columns",
      "schema": "public",
      "table": "notification"
    },
    {
      "type": "integer",
      "typeSchema": null,
      "notNull": true,
      "dimensions": 0,
      "default": "0",
      "generated": null,
      "identity": null,
      "name": "totalClicked",
      "entityType": "columns",
      "schema": "public",
      "table": "notification"
    },
    {
      "type": "timestamp(3) with time zone",
      "typeSchema": null,
      "notNull": false,
      "dimensions": 0,
      "default": null,
      "generated": null,
      "identity": null,
      "name": "sentAt",
      "entityType": "columns",
      "schema": "public",
      "table": "notification"
    },
    {
      "type": "timestamp(3) with time zone",
      "typeSchema": null,
      "notNull": true,
      "dimensions": 0,
      "default": "now()",
      "generated": null,
      "identity": null,
      "name": "createdAt",
      "entityType": "columns",
      "schema": "public",
      "table": "notification"
    },
    {
      "type": "timestamp(3) with time zone",
      "typeSchema": null,
      "notNull": true,
      "dimensions": 0,
      "default": "now()",
      "generated": null,
      "identity": null,
      "name": "updatedAt",
      "entityType": "columns",
      "schema": "public",
      "table": "notification"
    },
    {
      "type": "uuid",
      "typeSchema": null,
      "notNull": true,
      "dimensions": 0,
      "default": null,
      "generated": null,
      "identity": null,
      "name": "id",
      "entityType": "columns",
      "schema": "public",
      "table": "subscriber"
    },
    {
      "type": "uuid",
      "typeSchema": null,
      "notNull": true,
      "dimensions": 0,
      "default": null,
      "generated": null,
      "identity": null,
      "name": "appId",
      "entityType": "columns",
      "schema": "public",
      "table": "subscriber"
    },
    {
      "type": "text",
      "typeSchema": null,
      "notNull": true,
      "dimensions": 0,
      "default": null,
      "generated": null,
      "identity": null,
      "name": "externalId",
      "entityType": "columns",
      "schema": "public",
      "table": "subscriber"
    },
    {
      "type": "text",
      "typeSchema": null,
      "notNull": false,
      "dimensions": 0,
      "default": null,
      "generated": null,
      "identity": null,
      "name": "email",
      "entityType": "columns",
      "schema": "public",
      "table": "subscriber"
    },
    {
      "type": "text",
      "typeSchema": null,
      "notNull": false,
      "dimensions": 0,
      "default": null,
      "generated": null,
      "identity": null,
      "name": "phone",
      "entityType": "columns",
      "schema": "public",
      "table": "subscriber"
    },
    {
      "type": "text",
      "typeSchema": null,
      "notNull": false,
      "dimensions": 0,
      "default": null,
      "generated": null,
      "identity": null,
      "name": "locale",
      "entityType": "columns",
      "schema": "public",
      "table": "subscriber"
    },
    {
      "type": "jsonb",
      "typeSchema": null,
      "notNull": false,
      "dimensions": 0,
      "default": null,
      "generated": null,
      "identity": null,
      "name": "metadata",
      "entityType": "columns",
      "schema": "public",
      "table": "subscriber"
    },
    {
      "type": "timestamp(3) with time zone",
      "typeSchema": null,
      "notNull": true,
      "dimensions": 0,
      "default": "now()",
      "generated": null,
      "identity": null,
      "name": "createdAt",
      "entityType": "columns",
      "schema": "public",
      "table": "subscriber"
    },
    {
      "type": "timestamp(3) with time zone",
      "typeSchema": null,
      "notNull": true,
      "dimensions": 0,
      "default": "now()",
      "generated": null,
      "identity": null,
      "name": "updatedAt",
      "entityType": "columns",
      "schema": "public",
      "table": "subscriber"
    },
    {
      "type": "uuid",
      "typeSchema": null,
      "notNull": true,
      "dimensions": 0,
      "default": null,
      "generated": null,
      "identity": null,
      "name": "id",
      "entityType": "columns",
      "schema": "public",
      "table": "subscriberDevice"
    },
    {
      "type": "uuid",
      "typeSchema": null,
      "notNull": true,
      "dimensions": 0,
      "default": null,
      "generated": null,
      "identity": null,
      "name": "subscriberId",
      "entityType": "columns",
      "schema": "public",
      "table": "subscriberDevice"
    },
    {
      "type": "uuid",
      "typeSchema": null,
      "notNull": true,
      "dimensions": 0,
      "default": null,
      "generated": null,
      "identity": null,
      "name": "deviceId",
      "entityType": "columns",
      "schema": "public",
      "table": "subscriberDevice"
    },
    {
      "type": "timestamp(3) with time zone",
      "typeSchema": null,
      "notNull": true,
      "dimensions": 0,
      "default": "now()",
      "generated": null,
      "identity": null,
      "name": "createdAt",
      "entityType": "columns",
      "schema": "public",
      "table": "subscriberDevice"
    },
    {
      "type": "uuid",
      "typeSchema": null,
      "notNull": true,
      "dimensions": 0,
      "default": null,
      "generated": null,
      "identity": null,
      "name": "id",
      "entityType": "columns",
      "schema": "public",
      "table": "subscriberPreference"
    },
    {
      "type": "uuid",
      "typeSchema": null,
      "notNull": true,
      "dimensions": 0,
      "default": null,
      "generated": null,
      "identity": null,
      "name": "subscriberId",
      "entityType": "columns",
      "schema": "public",
      "table": "subscriberPreference"
    },
    {
      "type": "text",
      "typeSchema": null,
      "notNull": true,
      "dimensions": 0,
      "default": null,
      "generated": null,
      "identity": null,
      "name": "category",
      "entityType": "columns",
      "schema": "public",
      "table": "subscriberPreference"
    },
    {
      "type": "channelType",
      "typeSchema": "public",
      "notNull": true,
      "dimensions": 0,
      "default": null,
      "generated": null,
      "identity": null,
      "name": "channelType",
      "entityType": "columns",
      "schema": "public",
      "table": "subscriberPreference"
    },
    {
      "type": "boolean",
      "typeSchema": null,
      "notNull": true,
      "dimensions": 0,
      "default": "true",
      "generated": null,
      "identity": null,
      "name": "enabled",
      "entityType": "columns",
      "schema": "public",
      "table": "subscriberPreference"
    },
    {
      "type": "timestamp(3) with time zone",
      "typeSchema": null,
      "notNull": true,
      "dimensions": 0,
      "default": "now()",
      "generated": null,
      "identity": null,
      "name": "createdAt",
      "entityType": "columns",
      "schema": "public",
      "table": "subscriberPreference"
    },
    {
      "type": "timestamp(3) with time zone",
      "typeSchema": null,
      "notNull": true,
      "dimensions": 0,
      "default": "now()",
      "generated": null,
      "identity": null,
      "name": "updatedAt",
      "entityType": "columns",
      "schema": "public",
      "table": "subscriberPreference"
    },
    {
      "type": "uuid",
      "typeSchema": null,
      "notNull": true,
      "dimensions": 0,
      "default": null,
      "generated": null,
      "identity": null,
      "name": "id",
      "entityType": "columns",
      "schema": "public",
      "table": "template"
    },
    {
      "type": "uuid",
      "typeSchema": null,
      "notNull": true,
      "dimensions": 0,
      "default": null,
      "generated": null,
      "identity": null,
      "name": "appId",
      "entityType": "columns",
      "schema": "public",
      "table": "template"
    },
    {
      "type": "uuid",
      "typeSchema": null,
      "notNull": false,
      "dimensions": 0,
      "default": null,
      "generated": null,
      "identity": null,
      "name": "channelId",
      "entityType": "columns",
      "schema": "public",
      "table": "template"
    },
    {
      "type": "text",
      "typeSchema": null,
      "notNull": true,
      "dimensions": 0,
      "default": null,
      "generated": null,
      "identity": null,
      "name": "name",
      "entityType": "columns",
      "schema": "public",
      "table": "template"
    },
    {
      "type": "channelType",
      "typeSchema": "public",
      "notNull": true,
      "dimensions": 0,
      "default": null,
      "generated": null,
      "identity": null,
      "name": "channelType",
      "entityType": "columns",
      "schema": "public",
      "table": "template"
    },
    {
      "type": "text",
      "typeSchema": null,
      "notNull": false,
      "dimensions": 0,
      "default": null,
      "generated": null,
      "identity": null,
      "name": "subject",
      "entityType": "columns",
      "schema": "public",
      "table": "template"
    },
    {
      "type": "text",
      "typeSchema": null,
      "notNull": true,
      "dimensions": 0,
      "default": null,
      "generated": null,
      "identity": null,
      "name": "body",
      "entityType": "columns",
      "schema": "public",
      "table": "template"
    },
    {
      "type": "text",
      "typeSchema": null,
      "notNull": false,
      "dimensions": 0,
      "default": null,
      "generated": null,
      "identity": null,
      "name": "htmlBody",
      "entityType": "columns",
      "schema": "public",
      "table": "template"
    },
    {
      "type": "timestamp(3) with time zone",
      "typeSchema": null,
      "notNull": true,
      "dimensions": 0,
      "default": "now()",
      "generated": null,
      "identity": null,
      "name": "createdAt",
      "entityType": "columns",
      "schema": "public",
      "table": "template"
    },
    {
      "type": "timestamp(3) with time zone",
      "typeSchema": null,
      "notNull": true,
      "dimensions": 0,
      "default": "now()",
      "generated": null,
      "identity": null,
      "name": "updatedAt",
      "entityType": "columns",
      "schema": "public",
      "table": "template"
    },
    {
      "type": "uuid",
      "typeSchema": null,
      "notNull": true,
      "dimensions": 0,
      "default": null,
      "generated": null,
      "identity": null,
      "name": "id",
      "entityType": "columns",
      "schema": "public",
      "table": "workflow"
    },
    {
      "type": "uuid",
      "typeSchema": null,
      "notNull": true,
      "dimensions": 0,
      "default": null,
      "generated": null,
      "identity": null,
      "name": "appId",
      "entityType": "columns",
      "schema": "public",
      "table": "workflow"
    },
    {
      "type": "text",
      "typeSchema": null,
      "notNull": true,
      "dimensions": 0,
      "default": null,
      "generated": null,
      "identity": null,
      "name": "name",
      "entityType": "columns",
      "schema": "public",
      "table": "workflow"
    },
    {
      "type": "text",
      "typeSchema": null,
      "notNull": true,
      "dimensions": 0,
      "default": null,
      "generated": null,
      "identity": null,
      "name": "triggerIdentifier",
      "entityType": "columns",
      "schema": "public",
      "table": "workflow"
    },
    {
      "type": "workflowTriggerType",
      "typeSchema": "public",
      "notNull": true,
      "dimensions": 0,
      "default": "'EVENT'",
      "generated": null,
      "identity": null,
      "name": "triggerType",
      "entityType": "columns",
      "schema": "public",
      "table": "workflow"
    },
    {
      "type": "workflowStatus",
      "typeSchema": "public",
      "notNull": true,
      "dimensions": 0,
      "default": "'DRAFT'",
      "generated": null,
      "identity": null,
      "name": "status",
      "entityType": "columns",
      "schema": "public",
      "table": "workflow"
    },
    {
      "type": "jsonb",
      "typeSchema": null,
      "notNull": false,
      "dimensions": 0,
      "default": null,
      "generated": null,
      "identity": null,
      "name": "flowLayout",
      "entityType": "columns",
      "schema": "public",
      "table": "workflow"
    },
    {
      "type": "timestamp(3) with time zone",
      "typeSchema": null,
      "notNull": true,
      "dimensions": 0,
      "default": "now()",
      "generated": null,
      "identity": null,
      "name": "createdAt",
      "entityType": "columns",
      "schema": "public",
      "table": "workflow"
    },
    {
      "type": "timestamp(3) with time zone",
      "typeSchema": null,
      "notNull": true,
      "dimensions": 0,
      "default": "now()",
      "generated": null,
      "identity": null,
      "name": "updatedAt",
      "entityType": "columns",
      "schema": "public",
      "table": "workflow"
    },
    {
      "type": "uuid",
      "typeSchema": null,
      "notNull": true,
      "dimensions": 0,
      "default": null,
      "generated": null,
      "identity": null,
      "name": "id",
      "entityType": "columns",
      "schema": "public",
      "table": "workflowExecution"
    },
    {
      "type": "uuid",
      "typeSchema": null,
      "notNull": true,
      "dimensions": 0,
      "default": null,
      "generated": null,
      "identity": null,
      "name": "workflowId",
      "entityType": "columns",
      "schema": "public",
      "table": "workflowExecution"
    },
    {
      "type": "uuid",
      "typeSchema": null,
      "notNull": false,
      "dimensions": 0,
      "default": null,
      "generated": null,
      "identity": null,
      "name": "subscriberId",
      "entityType": "columns",
      "schema": "public",
      "table": "workflowExecution"
    },
    {
      "type": "text",
      "typeSchema": null,
      "notNull": true,
      "dimensions": 0,
      "default": null,
      "generated": null,
      "identity": null,
      "name": "triggerIdentifier",
      "entityType": "columns",
      "schema": "public",
      "table": "workflowExecution"
    },
    {
      "type": "jsonb",
      "typeSchema": null,
      "notNull": false,
      "dimensions": 0,
      "default": null,
      "generated": null,
      "identity": null,
      "name": "payload",
      "entityType": "columns",
      "schema": "public",
      "table": "workflowExecution"
    },
    {
      "type": "workflowExecutionStatus",
      "typeSchema": "public",
      "notNull": true,
      "dimensions": 0,
      "default": "'RUNNING'",
      "generated": null,
      "identity": null,
      "name": "status",
      "entityType": "columns",
      "schema": "public",
      "table": "workflowExecution"
    },
    {
      "type": "integer",
      "typeSchema": null,
      "notNull": true,
      "dimensions": 0,
      "default": "0",
      "generated": null,
      "identity": null,
      "name": "currentStepOrder",
      "entityType": "columns",
      "schema": "public",
      "table": "workflowExecution"
    },
    {
      "type": "text",
      "typeSchema": null,
      "notNull": false,
      "dimensions": 0,
      "default": null,
      "generated": null,
      "identity": null,
      "name": "errorMessage",
      "entityType": "columns",
      "schema": "public",
      "table": "workflowExecution"
    },
    {
      "type": "timestamp(3) with time zone",
      "typeSchema": null,
      "notNull": true,
      "dimensions": 0,
      "default": "now()",
      "generated": null,
      "identity": null,
      "name": "startedAt",
      "entityType": "columns",
      "schema": "public",
      "table": "workflowExecution"
    },
    {
      "type": "timestamp(3) with time zone",
      "typeSchema": null,
      "notNull": false,
      "dimensions": 0,
      "default": null,
      "generated": null,
      "identity": null,
      "name": "completedAt",
      "entityType": "columns",
      "schema": "public",
      "table": "workflowExecution"
    },
    {
      "type": "timestamp(3) with time zone",
      "typeSchema": null,
      "notNull": true,
      "dimensions": 0,
      "default": "now()",
      "generated": null,
      "identity": null,
      "name": "createdAt",
      "entityType": "columns",
      "schema": "public",
      "table": "workflowExecution"
    },
    {
      "type": "timestamp(3) with time zone",
      "typeSchema": null,
      "notNull": true,
      "dimensions": 0,
      "default": "now()",
      "generated": null,
      "identity": null,
      "name": "updatedAt",
      "entityType": "columns",
      "schema": "public",
      "table": "workflowExecution"
    },
    {
      "type": "uuid",
      "typeSchema": null,
      "notNull": true,
      "dimensions": 0,
      "default": null,
      "generated": null,
      "identity": null,
      "name": "id",
      "entityType": "columns",
      "schema": "public",
      "table": "workflowStep"
    },
    {
      "type": "uuid",
      "typeSchema": null,
      "notNull": true,
      "dimensions": 0,
      "default": null,
      "generated": null,
      "identity": null,
      "name": "workflowId",
      "entityType": "columns",
      "schema": "public",
      "table": "workflowStep"
    },
    {
      "type": "text",
      "typeSchema": null,
      "notNull": false,
      "dimensions": 0,
      "default": null,
      "generated": null,
      "identity": null,
      "name": "nodeId",
      "entityType": "columns",
      "schema": "public",
      "table": "workflowStep"
    },
    {
      "type": "workflowStepType",
      "typeSchema": "public",
      "notNull": true,
      "dimensions": 0,
      "default": null,
      "generated": null,
      "identity": null,
      "name": "type",
      "entityType": "columns",
      "schema": "public",
      "table": "workflowStep"
    },
    {
      "type": "integer",
      "typeSchema": null,
      "notNull": true,
      "dimensions": 0,
      "default": null,
      "generated": null,
      "identity": null,
      "name": "order",
      "entityType": "columns",
      "schema": "public",
      "table": "workflowStep"
    },
    {
      "type": "jsonb",
      "typeSchema": null,
      "notNull": false,
      "dimensions": 0,
      "default": null,
      "generated": null,
      "identity": null,
      "name": "config",
      "entityType": "columns",
      "schema": "public",
      "table": "workflowStep"
    },
    {
      "type": "timestamp(3) with time zone",
      "typeSchema": null,
      "notNull": true,
      "dimensions": 0,
      "default": "now()",
      "generated": null,
      "identity": null,
      "name": "createdAt",
      "entityType": "columns",
      "schema": "public",
      "table": "workflowStep"
    },
    {
      "type": "timestamp(3) with time zone",
      "typeSchema": null,
      "notNull": true,
      "dimensions": 0,
      "default": "now()",
      "generated": null,
      "identity": null,
      "name": "updatedAt",
      "entityType": "columns",
      "schema": "public",
      "table": "workflowStep"
    },
    {
      "nameExplicit": true,
      "columns": [
        {
          "value": "appId",
          "isExpression": false,
          "asc": true,
          "nullsFirst": false,
          "opclass": null
        }
      ],
      "isUnique": false,
      "where": null,
      "with": "",
      "method": "btree",
      "concurrently": false,
      "name": "channel_app_id_idx",
      "entityType": "indexes",
      "schema": "public",
      "table": "channel"
    },
    {
      "nameExplicit": true,
      "columns": [
        {
          "value": "appId",
          "isExpression": false,
          "asc": true,
          "nullsFirst": false,
          "opclass": null
        },
        {
          "value": "type",
          "isExpression": false,
          "asc": true,
          "nullsFirst": false,
          "opclass": null
        }
      ],
      "isUnique": false,
      "where": null,
      "with": "",
      "method": "btree",
      "concurrently": false,
      "name": "channel_app_type_idx",
      "entityType": "indexes",
      "schema": "public",
      "table": "channel"
    },
    {
      "nameExplicit": true,
      "columns": [
        {
          "value": "notificationId",
          "isExpression": false,
          "asc": true,
          "nullsFirst": false,
          "opclass": null
        }
      ],
      "isUnique": false,
      "where": null,
      "with": "",
      "method": "btree",
      "concurrently": false,
      "name": "delivery_log_notification_id_idx",
      "entityType": "indexes",
      "schema": "public",
      "table": "deliveryLog"
    },
    {
      "nameExplicit": true,
      "columns": [
        {
          "value": "createdAt",
          "isExpression": false,
          "asc": true,
          "nullsFirst": false,
          "opclass": null
        }
      ],
      "isUnique": false,
      "where": null,
      "with": "",
      "method": "btree",
      "concurrently": false,
      "name": "delivery_log_created_at_idx",
      "entityType": "indexes",
      "schema": "public",
      "table": "deliveryLog"
    },
    {
      "nameExplicit": true,
      "columns": [
        {
          "value": "status",
          "isExpression": false,
          "asc": true,
          "nullsFirst": false,
          "opclass": null
        }
      ],
      "isUnique": false,
      "where": null,
      "with": "",
      "method": "btree",
      "concurrently": false,
      "name": "delivery_log_status_idx",
      "entityType": "indexes",
      "schema": "public",
      "table": "deliveryLog"
    },
    {
      "nameExplicit": true,
      "columns": [
        {
          "value": "notificationId",
          "isExpression": false,
          "asc": true,
          "nullsFirst": false,
          "opclass": null
        },
        {
          "value": "deviceId",
          "isExpression": false,
          "asc": true,
          "nullsFirst": false,
          "opclass": null
        }
      ],
      "isUnique": false,
      "where": null,
      "with": "",
      "method": "btree",
      "concurrently": false,
      "name": "delivery_log_notification_device_idx",
      "entityType": "indexes",
      "schema": "public",
      "table": "deliveryLog"
    },
    {
      "nameExplicit": true,
      "columns": [
        {
          "value": "appId",
          "isExpression": false,
          "asc": true,
          "nullsFirst": false,
          "opclass": null
        }
      ],
      "isUnique": false,
      "where": null,
      "with": "",
      "method": "btree",
      "concurrently": false,
      "name": "device_app_id_idx",
      "entityType": "indexes",
      "schema": "public",
      "table": "device"
    },
    {
      "nameExplicit": true,
      "columns": [
        {
          "value": "appId",
          "isExpression": false,
          "asc": true,
          "nullsFirst": false,
          "opclass": null
        },
        {
          "value": "status",
          "isExpression": false,
          "asc": true,
          "nullsFirst": false,
          "opclass": null
        }
      ],
      "isUnique": false,
      "where": null,
      "with": "",
      "method": "btree",
      "concurrently": false,
      "name": "device_app_id_status_idx",
      "entityType": "indexes",
      "schema": "public",
      "table": "device"
    },
    {
      "nameExplicit": true,
      "columns": [
        {
          "value": "token",
          "isExpression": false,
          "asc": true,
          "nullsFirst": false,
          "opclass": null
        }
      ],
      "isUnique": false,
      "where": null,
      "with": "",
      "method": "btree",
      "concurrently": false,
      "name": "device_token_idx",
      "entityType": "indexes",
      "schema": "public",
      "table": "device"
    },
    {
      "nameExplicit": true,
      "columns": [
        {
          "value": "appId",
          "isExpression": false,
          "asc": true,
          "nullsFirst": false,
          "opclass": null
        }
      ],
      "isUnique": false,
      "where": null,
      "with": "",
      "method": "btree",
      "concurrently": false,
      "name": "hook_app_id_idx",
      "entityType": "indexes",
      "schema": "public",
      "table": "hook"
    },
    {
      "nameExplicit": true,
      "columns": [
        {
          "value": "status",
          "isExpression": false,
          "asc": true,
          "nullsFirst": false,
          "opclass": null
        },
        {
          "value": "scheduledAt",
          "isExpression": false,
          "asc": true,
          "nullsFirst": false,
          "opclass": null
        }
      ],
      "isUnique": false,
      "where": null,
      "with": "",
      "method": "btree",
      "concurrently": false,
      "name": "notification_status_scheduled_at_idx",
      "entityType": "indexes",
      "schema": "public",
      "table": "notification"
    },
    {
      "nameExplicit": true,
      "columns": [
        {
          "value": "appId",
          "isExpression": false,
          "asc": true,
          "nullsFirst": false,
          "opclass": null
        }
      ],
      "isUnique": false,
      "where": null,
      "with": "",
      "method": "btree",
      "concurrently": false,
      "name": "notification_app_id_idx",
      "entityType": "indexes",
      "schema": "public",
      "table": "notification"
    },
    {
      "nameExplicit": true,
      "columns": [
        {
          "value": "createdAt",
          "isExpression": false,
          "asc": true,
          "nullsFirst": false,
          "opclass": null
        }
      ],
      "isUnique": false,
      "where": null,
      "with": "",
      "method": "btree",
      "concurrently": false,
      "name": "notification_created_at_idx",
      "entityType": "indexes",
      "schema": "public",
      "table": "notification"
    },
    {
      "nameExplicit": true,
      "columns": [
        {
          "value": "appId",
          "isExpression": false,
          "asc": true,
          "nullsFirst": false,
          "opclass": null
        }
      ],
      "isUnique": false,
      "where": null,
      "with": "",
      "method": "btree",
      "concurrently": false,
      "name": "subscriber_app_id_idx",
      "entityType": "indexes",
      "schema": "public",
      "table": "subscriber"
    },
    {
      "nameExplicit": true,
      "columns": [
        {
          "value": "externalId",
          "isExpression": false,
          "asc": true,
          "nullsFirst": false,
          "opclass": null
        }
      ],
      "isUnique": false,
      "where": null,
      "with": "",
      "method": "btree",
      "concurrently": false,
      "name": "subscriber_external_id_idx",
      "entityType": "indexes",
      "schema": "public",
      "table": "subscriber"
    },
    {
      "nameExplicit": true,
      "columns": [
        {
          "value": "appId",
          "isExpression": false,
          "asc": true,
          "nullsFirst": false,
          "opclass": null
        },
        {
          "value": "externalId",
          "isExpression": false,
          "asc": true,
          "nullsFirst": false,
          "opclass": null
        }
      ],
      "isUnique": false,
      "where": null,
      "with": "",
      "method": "btree",
      "concurrently": false,
      "name": "subscriber_app_external_unique_idx",
      "entityType": "indexes",
      "schema": "public",
      "table": "subscriber"
    },
    {
      "nameExplicit": true,
      "columns": [
        {
          "value": "subscriberId",
          "isExpression": false,
          "asc": true,
          "nullsFirst": false,
          "opclass": null
        }
      ],
      "isUnique": false,
      "where": null,
      "with": "",
      "method": "btree",
      "concurrently": false,
      "name": "subscriberDevice_subscriber_id_idx",
      "entityType": "indexes",
      "schema": "public",
      "table": "subscriberDevice"
    },
    {
      "nameExplicit": true,
      "columns": [
        {
          "value": "deviceId",
          "isExpression": false,
          "asc": true,
          "nullsFirst": false,
          "opclass": null
        }
      ],
      "isUnique": false,
      "where": null,
      "with": "",
      "method": "btree",
      "concurrently": false,
      "name": "subscriberDevice_device_id_idx",
      "entityType": "indexes",
      "schema": "public",
      "table": "subscriberDevice"
    },
    {
      "nameExplicit": true,
      "columns": [
        {
          "value": "subscriberId",
          "isExpression": false,
          "asc": true,
          "nullsFirst": false,
          "opclass": null
        }
      ],
      "isUnique": false,
      "where": null,
      "with": "",
      "method": "btree",
      "concurrently": false,
      "name": "subscriberPreference_subscriber_id_idx",
      "entityType": "indexes",
      "schema": "public",
      "table": "subscriberPreference"
    },
    {
      "nameExplicit": true,
      "columns": [
        {
          "value": "subscriberId",
          "isExpression": false,
          "asc": true,
          "nullsFirst": false,
          "opclass": null
        },
        {
          "value": "category",
          "isExpression": false,
          "asc": true,
          "nullsFirst": false,
          "opclass": null
        },
        {
          "value": "channelType",
          "isExpression": false,
          "asc": true,
          "nullsFirst": false,
          "opclass": null
        }
      ],
      "isUnique": false,
      "where": null,
      "with": "",
      "method": "btree",
      "concurrently": false,
      "name": "subscriberPreference_subscriber_category_channel_idx",
      "entityType": "indexes",
      "schema": "public",
      "table": "subscriberPreference"
    },
    {
      "nameExplicit": true,
      "columns": [
        {
          "value": "appId",
          "isExpression": false,
          "asc": true,
          "nullsFirst": false,
          "opclass": null
        }
      ],
      "isUnique": false,
      "where": null,
      "with": "",
      "method": "btree",
      "concurrently": false,
      "name": "template_app_id_idx",
      "entityType": "indexes",
      "schema": "public",
      "table": "template"
    },
    {
      "nameExplicit": true,
      "columns": [
        {
          "value": "channelId",
          "isExpression": false,
          "asc": true,
          "nullsFirst": false,
          "opclass": null
        }
      ],
      "isUnique": false,
      "where": null,
      "with": "",
      "method": "btree",
      "concurrently": false,
      "name": "template_channel_id_idx",
      "entityType": "indexes",
      "schema": "public",
      "table": "template"
    },
    {
      "nameExplicit": true,
      "columns": [
        {
          "value": "channelType",
          "isExpression": false,
          "asc": true,
          "nullsFirst": false,
          "opclass": null
        }
      ],
      "isUnique": false,
      "where": null,
      "with": "",
      "method": "btree",
      "concurrently": false,
      "name": "template_channel_type_idx",
      "entityType": "indexes",
      "schema": "public",
      "table": "template"
    },
    {
      "nameExplicit": true,
      "columns": [
        {
          "value": "appId",
          "isExpression": false,
          "asc": true,
          "nullsFirst": false,
          "opclass": null
        }
      ],
      "isUnique": false,
      "where": null,
      "with": "",
      "method": "btree",
      "concurrently": false,
      "name": "workflow_app_id_idx",
      "entityType": "indexes",
      "schema": "public",
      "table": "workflow"
    },
    {
      "nameExplicit": true,
      "columns": [
        {
          "value": "triggerIdentifier",
          "isExpression": false,
          "asc": true,
          "nullsFirst": false,
          "opclass": null
        }
      ],
      "isUnique": false,
      "where": null,
      "with": "",
      "method": "btree",
      "concurrently": false,
      "name": "workflow_trigger_identifier_idx",
      "entityType": "indexes",
      "schema": "public",
      "table": "workflow"
    },
    {
      "nameExplicit": true,
      "columns": [
        {
          "value": "appId",
          "isExpression": false,
          "asc": true,
          "nullsFirst": false,
          "opclass": null
        },
        {
          "value": "triggerIdentifier",
          "isExpression": false,
          "asc": true,
          "nullsFirst": false,
          "opclass": null
        }
      ],
      "isUnique": false,
      "where": null,
      "with": "",
      "method": "btree",
      "concurrently": false,
      "name": "workflow_app_trigger_unique_idx",
      "entityType": "indexes",
      "schema": "public",
      "table": "workflow"
    },
    {
      "nameExplicit": true,
      "columns": [
        {
          "value": "workflowId",
          "isExpression": false,
          "asc": true,
          "nullsFirst": false,
          "opclass": null
        }
      ],
      "isUnique": false,
      "where": null,
      "with": "",
      "method": "btree",
      "concurrently": false,
      "name": "workflowExecution_workflow_id_idx",
      "entityType": "indexes",
      "schema": "public",
      "table": "workflowExecution"
    },
    {
      "nameExplicit": true,
      "columns": [
        {
          "value": "subscriberId",
          "isExpression": false,
          "asc": true,
          "nullsFirst": false,
          "opclass": null
        }
      ],
      "isUnique": false,
      "where": null,
      "with": "",
      "method": "btree",
      "concurrently": false,
      "name": "workflowExecution_subscriber_id_idx",
      "entityType": "indexes",
      "schema": "public",
      "table": "workflowExecution"
    },
    {
      "nameExplicit": true,
      "columns": [
        {
          "value": "status",
          "isExpression": false,
          "asc": true,
          "nullsFirst": false,
          "opclass": null
        }
      ],
      "isUnique": false,
      "where": null,
      "with": "",
      "method": "btree",
      "concurrently": false,
      "name": "workflowExecution_status_idx",
      "entityType": "indexes",
      "schema": "public",
      "table": "workflowExecution"
    },
    {
      "nameExplicit": true,
      "columns": [
        {
          "value": "workflowId",
          "isExpression": false,
          "asc": true,
          "nullsFirst": false,
          "opclass": null
        }
      ],
      "isUnique": false,
      "where": null,
      "with": "",
      "method": "btree",
      "concurrently": false,
      "name": "workflowStep_workflow_id_idx",
      "entityType": "indexes",
      "schema": "public",
      "table": "workflowStep"
    },
    {
      "nameExplicit": true,
      "columns": [
        {
          "value": "workflowId",
          "isExpression": false,
          "asc": true,
          "nullsFirst": false,
          "opclass": null
        },
        {
          "value": "order",
          "isExpression": false,
          "asc": true,
          "nullsFirst": false,
          "opclass": null
        }
      ],
      "isUnique": false,
      "where": null,
      "with": "",
      "method": "btree",
      "concurrently": false,
      "name": "workflowStep_workflow_order_idx",
      "entityType": "indexes",
      "schema": "public",
      "table": "workflowStep"
    },
    {
      "nameExplicit": false,
      "columns": [
        "appId"
      ],
      "schemaTo": "public",
      "tableTo": "app",
      "columnsTo": [
        "id"
      ],
      "onUpdate": "NO ACTION",
      "onDelete": "CASCADE",
      "name": "apiKey_appId_app_id_fkey",
      "entityType": "fks",
      "schema": "public",
      "table": "apiKey"
    },
    {
      "nameExplicit": false,
      "columns": [
        "appId"
      ],
      "schemaTo": "public",
      "tableTo": "app",
      "columnsTo": [
        "id"
      ],
      "onUpdate": "NO ACTION",
      "onDelete": "CASCADE",
      "name": "channel_appId_app_id_fkey",
      "entityType": "fks",
      "schema": "public",
      "table": "channel"
    },
    {
      "nameExplicit": false,
      "columns": [
        "notificationId"
      ],
      "schemaTo": "public",
      "tableTo": "notification",
      "columnsTo": [
        "id"
      ],
      "onUpdate": "NO ACTION",
      "onDelete": "CASCADE",
      "name": "deliveryLog_notificationId_notification_id_fkey",
      "entityType": "fks",
      "schema": "public",
      "table": "deliveryLog"
    },
    {
      "nameExplicit": false,
      "columns": [
        "deviceId"
      ],
      "schemaTo": "public",
      "tableTo": "device",
      "columnsTo": [
        "id"
      ],
      "onUpdate": "NO ACTION",
      "onDelete": "CASCADE",
      "name": "deliveryLog_deviceId_device_id_fkey",
      "entityType": "fks",
      "schema": "public",
      "table": "deliveryLog"
    },
    {
      "nameExplicit": false,
      "columns": [
        "appId"
      ],
      "schemaTo": "public",
      "tableTo": "app",
      "columnsTo": [
        "id"
      ],
      "onUpdate": "NO ACTION",
      "onDelete": "CASCADE",
      "name": "device_appId_app_id_fkey",
      "entityType": "fks",
      "schema": "public",
      "table": "device"
    },
    {
      "nameExplicit": false,
      "columns": [
        "appId"
      ],
      "schemaTo": "public",
      "tableTo": "app",
      "columnsTo": [
        "id"
      ],
      "onUpdate": "NO ACTION",
      "onDelete": "CASCADE",
      "name": "hook_appId_app_id_fkey",
      "entityType": "fks",
      "schema": "public",
      "table": "hook"
    },
    {
      "nameExplicit": false,
      "columns": [
        "appId"
      ],
      "schemaTo": "public",
      "tableTo": "app",
      "columnsTo": [
        "id"
      ],
      "onUpdate": "NO ACTION",
      "onDelete": "CASCADE",
      "name": "notification_appId_app_id_fkey",
      "entityType": "fks",
      "schema": "public",
      "table": "notification"
    },
    {
      "nameExplicit": false,
      "columns": [
        "appId"
      ],
      "schemaTo": "public",
      "tableTo": "app",
      "columnsTo": [
        "id"
      ],
      "onUpdate": "NO ACTION",
      "onDelete": "CASCADE",
      "name": "subscriber_appId_app_id_fkey",
      "entityType": "fks",
      "schema": "public",
      "table": "subscriber"
    },
    {
      "nameExplicit": false,
      "columns": [
        "subscriberId"
      ],
      "schemaTo": "public",
      "tableTo": "subscriber",
      "columnsTo": [
        "id"
      ],
      "onUpdate": "NO ACTION",
      "onDelete": "CASCADE",
      "name": "subscriberDevice_subscriberId_subscriber_id_fkey",
      "entityType": "fks",
      "schema": "public",
      "table": "subscriberDevice"
    },
    {
      "nameExplicit": false,
      "columns": [
        "deviceId"
      ],
      "schemaTo": "public",
      "tableTo": "device",
      "columnsTo": [
        "id"
      ],
      "onUpdate": "NO ACTION",
      "onDelete": "CASCADE",
      "name": "subscriberDevice_deviceId_device_id_fkey",
      "entityType": "fks",
      "schema": "public",
      "table": "subscriberDevice"
    },
    {
      "nameExplicit": false,
      "columns": [
        "subscriberId"
      ],
      "schemaTo": "public",
      "tableTo": "subscriber",
      "columnsTo": [
        "id"
      ],
      "onUpdate": "NO ACTION",
      "onDelete": "CASCADE",
      "name": "subscriberPreference_subscriberId_subscriber_id_fkey",
      "entityType": "fks",
      "schema": "public",
      "table": "subscriberPreference"
    },
    {
      "nameExplicit": false,
      "columns": [
        "appId"
      ],
      "schemaTo": "public",
      "tableTo": "app",
      "columnsTo": [
        "id"
      ],
      "onUpdate": "NO ACTION",
      "onDelete": "CASCADE",
      "name": "template_appId_app_id_fkey",
      "entityType": "fks",
      "schema": "public",
      "table": "template"
    },
    {
      "nameExplicit": false,
      "columns": [
        "channelId"
      ],
      "schemaTo": "public",
      "tableTo": "channel",
      "columnsTo": [
        "id"
      ],
      "onUpdate": "NO ACTION",
      "onDelete": "SET NULL",
      "name": "template_channelId_channel_id_fkey",
      "entityType": "fks",
      "schema": "public",
      "table": "template"
    },
    {
      "nameExplicit": false,
      "columns": [
        "appId"
      ],
      "schemaTo": "public",
      "tableTo": "app",
      "columnsTo": [
        "id"
      ],
      "onUpdate": "NO ACTION",
      "onDelete": "CASCADE",
      "name": "workflow_appId_app_id_fkey",
      "entityType": "fks",
      "schema": "public",
      "table": "workflow"
    },
    {
      "nameExplicit": false,
      "columns": [
        "workflowId"
      ],
      "schemaTo": "public",
      "tableTo": "workflow",
      "columnsTo": [
        "id"
      ],
      "onUpdate": "NO ACTION",
      "onDelete": "CASCADE",
      "name": "workflowExecution_workflowId_workflow_id_fkey",
      "entityType": "fks",
      "schema": "public",
      "table": "workflowExecution"
    },
    {
      "nameExplicit": false,
      "columns": [
        "subscriberId"
      ],
      "schemaTo": "public",
      "tableTo": "subscriber",
      "columnsTo": [
        "id"
      ],
      "onUpdate": "NO ACTION",
      "onDelete": "SET NULL",
      "name": "workflowExecution_subscriberId_subscriber_id_fkey",
      "entityType": "fks",
      "schema": "public",
      "table": "workflowExecution"
    },
    {
      "nameExplicit": false,
      "columns": [
        "workflowId"
      ],
      "schemaTo": "public",
      "tableTo": "workflow",
      "columnsTo": [
        "id"
      ],
      "onUpdate": "NO ACTION",
      "onDelete": "CASCADE",
      "name": "workflowStep_workflowId_workflow_id_fkey",
      "entityType": "fks",
      "schema": "public",
      "table": "workflowStep"
    },
    {
      "columns": [
        "id"
      ],
      "nameExplicit": false,
      "name": "apiKey_pkey",
      "schema": "public",
      "table": "apiKey",
      "entityType": "pks"
    },
    {
      "columns": [
        "id"
      ],
      "nameExplicit": false,
      "name": "app_pkey",
      "schema": "public",
      "table": "app",
      "entityType": "pks"
    },
    {
      "columns": [
        "id"
      ],
      "nameExplicit": false,
      "name": "channel_pkey",
      "schema": "public",
      "table": "channel",
      "entityType": "pks"
    },
    {
      "columns": [
        "id"
      ],
      "nameExplicit": false,
      "name": "deliveryLog_pkey",
      "schema": "public",
      "table": "deliveryLog",
      "entityType": "pks"
    },
    {
      "columns": [
        "id"
      ],
      "nameExplicit": false,
      "name": "device_pkey",
      "schema": "public",
      "table": "device",
      "entityType": "pks"
    },
    {
      "columns": [
        "id"
      ],
      "nameExplicit": false,
      "name": "hook_pkey",
      "schema": "public",
      "table": "hook",
      "entityType": "pks"
    },
    {
      "columns": [
        "id"
      ],
      "nameExplicit": false,
      "name": "notification_pkey",
      "schema": "public",
      "table": "notification",
      "entityType": "pks"
    },
    {
      "columns": [
        "id"
      ],
      "nameExplicit": false,
      "name": "subscriber_pkey",
      "schema": "public",
      "table": "subscriber",
      "entityType": "pks"
    },
    {
      "columns": [
        "id"
      ],
      "nameExplicit": false,
      "name": "subscriberDevice_pkey",
      "schema": "public",
      "table": "subscriberDevice",
      "entityType": "pks"
    },
    {
      "columns": [
        "id"
      ],
      "nameExplicit": false,
      "name": "subscriberPreference_pkey",
      "schema": "public",
      "table": "subscriberPreference",
      "entityType": "pks"
    },
    {
      "columns": [
        "id"
      ],
      "nameExplicit": false,
      "name": "template_pkey",
      "schema": "public",
      "table": "template",
      "entityType": "pks"
    },
    {
      "columns": [
        "id"
      ],
      "nameExplicit": false,
      "name": "workflow_pkey",
      "schema": "public",
      "table": "workflow",
      "entityType": "pks"
    },
    {
      "columns": [
        "id"
      ],
      "nameExplicit": false,
      "name": "workflowExecution_pkey",
      "schema": "public",
      "table": "workflowExecution",
      "entityType": "pks"
    },
    {
      "columns": [
        "id"
      ],
      "nameExplicit": false,
      "name": "workflowStep_pkey",
      "schema": "public",
      "table": "workflowStep",
      "entityType": "pks"
    },
    {
      "nameExplicit": true,
      "columns": [
        "appId",
        "token",
        "userId"
      ],
      "nullsNotDistinct": false,
      "name": "device_appId_token_userId_unique",
      "entityType": "uniques",
      "schema": "public",
      "table": "device"
    },
    {
      "nameExplicit": false,
      "columns": [
        "key"
      ],
      "nullsNotDistinct": false,
      "name": "apiKey_key_key",
      "schema": "public",
      "table": "apiKey",
      "entityType": "uniques"
    },
    {
      "nameExplicit": false,
      "columns": [
        "slug"
      ],
      "nullsNotDistinct": false,
      "name": "app_slug_key",
      "schema": "public",
      "table": "app",
      "entityType": "uniques"
    },
    {
      "nameExplicit": false,
      "columns": [
        "apiKey"
      ],
      "nullsNotDistinct": false,
      "name": "app_apiKey_key",
      "schema": "public",
      "table": "app",
      "entityType": "uniques"
    }
  ],
  "renames": []
}